{"cameraMode":{"drawMode":0,"name":"Shaded","section":"Shading Mode"},"sceneLighting":true,"audioPlay":false,"sceneViewState":{"m_AlwaysRefresh":true,"showFog":true,"showSkybox":true,"showFlares":true,"showImageEffects":true,"showParticleSystems":true,"showVisualEffectGraphs":true,"m_FxEnabled":true},"in2DMode":false,"pivot":{"x":-2.7873268127441408,"y":8.36850643157959,"z":31.943822860717775},"rotation":{"x":0.7071068286895752,"y":0.0,"z":0.0,"w":0.7071068286895752},"size":28.177846908569337,"orthographic":false}